{
  "categories": [
    {
      "id": "1",
      "category_name": "Trabalho"
    },
    {
      "id": "2",
      "category_name": "Moradia"
    },
    {
      "id": "3",
      "category_name": "Alimentação"
    },
    {
      "id": "4",
      "category_name": "Lazer"
    },
    {
      "id": "5",
      "category_name": "Outros"
    }
  ],
  "transactions": [
    {
      "id": "52cf",
      "date": "2025-01-03",
      "title": "Salário Giselle",
      "value": 5502,
      "type": "receita",
      "categoryId": "1",
      "category_name": "Trabalho"
    },
    {
      "id": "4911",
      "date": "2025-01-03",
      "title": "Salário Tiago",
      "value": 5100,
      "type": "receita",
      "categoryId": "1",
      "category_name": "Trabalho"
    },
    {
      "id": "6bd9",
      "date": "2025-01-03",
      "title": "Internet",
      "value": 100,
      "type": "despesa",
      "categoryId": "2",
      "category_name": "Moradia",
      "styleClass": "despesa"
    },
    {
      "id": "e18b",
      "date": "2025-01-03",
      "title": "teste3",
      "value": 20,
      "type": "despesa",
      "categoryId": "2",
      "category_name": "Moradia",
      "styleClass": "despesa"
    },
    {
      "id": "8fa7",
      "date": "2025-01-03",
      "title": "teste4",
      "value": 55,
      "type": "despesa",
      "categoryId": "3",
      "category_name": "Alimentação",
      "styleClass": "despesa"
    },
    {
      "id": "5de7",
      "date": "2025-01-05",
      "title": "Freelance",
      "value": 250,
      "type": "receita",
      "categoryId": "1",
      "category_name": "Trabalho"
    },
    {
      "id": "f059",
      "date": "2025-01-03",
      "title": "teste7",
      "value": 88,
      "type": "despesa",
      "categoryId": "5",
      "category_name": "Outros",
      "styleClass": "despesa"
    },
    {
      "id": "3664",
      "date": "2025-01-03",
      "title": "teste8",
      "value": 10,
      "type": "despesa",
      "categoryId": "4",
      "category_name": "Lazer",
      "styleClass": "despesa"
    },
    {
      "id": "e206",
      "date": "2025-01-03",
      "title": "teste10",
      "value": 1111,
      "type": "despesa",
      "categoryId": "3",
      "category_name": "Alimentação",
      "styleClass": "despesa"
    },
    {
      "id": "4add",
      "date": "2025-01-03",
      "title": "teste12",
      "value": 12121,
      "type": "despesa",
      "categoryId": "5",
      "category_name": "Outros",
      "styleClass": "despesa"
    },
    {
      "id": "3dba",
      "date": "2025-01-03",
      "title": "teste11",
      "value": 11,
      "type": "despesa",
      "categoryId": "4",
      "category_name": "Lazer",
      "styleClass": "despesa"
    }
  ]
}